soc_monitor/__init__.py
soc_monitor/cli.py
soc_monitor/server.py
soc_monitor/utils.py
soc_monitor-0.2.0.dist-info/METADATA
soc_monitor-0.2.0.dist-info/WHEEL
soc_monitor-0.2.0.dist-info/entry_points.txt
soc_monitor-0.2.0.dist-info/top_level.txt
soc_monitor-0.2.0.dist-info/RECORD
