Metadata-Version: 2.2
Name: soc_monitor
Version: 0.2.0
Summary: A comprehensive system monitoring tool powered by FastAPI.
Home-page: https://github.com/Shreyashs98/soc-monitor
Author: Shreyas H S
Author-email: s09082003@gmail.com
Keywords: system monitoring fastapi uvicorn psutil speedtest-cli
Classifier: Development Status :: 4 - Beta
Classifier: Intended Audience :: Developers
Classifier: Topic :: System :: Monitoring
Classifier: License :: OSI Approved :: MIT License
Classifier: Programming Language :: Python :: 3
Classifier: Programming Language :: Python :: 3.7
Classifier: Programming Language :: Python :: 3.8
Classifier: Programming Language :: Python :: 3.9
Classifier: Operating System :: OS Independent
Classifier: Framework :: FastAPI
Requires-Dist: fastapi
Requires-Dist: uvicorn
Requires-Dist: psutil
Requires-Dist: speedtest-cli
Dynamic: author
Dynamic: author-email
Dynamic: classifier
Dynamic: description
Dynamic: description-content-type
Dynamic: home-page
Dynamic: keywords
Dynamic: requires-dist
Dynamic: summary
